{
    "name": "Aniia Hamilton",
    "avatar": "https://media.licdn.com/dms/image/C4E03AQEKWC2VX-C1qA/profile-displayphoto-shrink_800_800/0/1651517690240?e=1681344000&v=beta&t=xZps3Gjdyc5qR70DKwxd9obhWTfgc2hqByuNNWa-flc",
    "links": [
        {
            "title": "LinkedIn",
            "href": "https://www.linkedin.com/in/aniia-hamilton/",
            "image": "logos_linkedin-icon.svg"
        },
        {
            "title": "GitHub",
            "href": "https://github.com/aniiaham",
            "image": "ant-design_github-filled.svg"
        },
        {
            "title": "Instagram",
            "href": "https://www.instagram.com/aniiahamilton/",
            "image": "skill-icons_instagram.svg"
        }
    ],
    "socials": [
        {
            "title": "Instagram",
            "href": "https://www.instagram.com/aniiahamilton/"
        },
        {
            "title": "LinkedIn",
            "href": "https://www.linkedin.com/in/aniia-hamilton/"
        },
        {
            "title": "GitHub",
            "href": "https://github.com/aniiaham"
        }
    ]
}